strutex/__init__.py
strutex/adapters.py
strutex/cache/__init__.py
strutex/cache/base.py
strutex/cache/file.py
strutex/cache/memory.py
strutex/cache/sqlite.py
strutex/cli.py
strutex/context.py
strutex/documents/__init__.py
strutex/documents/file_utils.py
strutex/documents/spreadsheet.py
strutex/documents/text.py
strutex/exceptions.py
strutex/extractors/__init__.py
strutex/extractors/excel.py
strutex/extractors/formatted.py
strutex/extractors/gliner.py
strutex/extractors/image.py
strutex/extractors/pdf.py
strutex/input.py
strutex/integrations/__init__.py
strutex/integrations/fastapi.py
strutex/integrations/haystack.py
strutex/integrations/langchain.py
strutex/integrations/llamaindex.py
strutex/integrations/unstructured.py
strutex/log_utils.py
strutex/plugins/__init__.py
strutex/plugins/base.py
strutex/plugins/discovery.py
strutex/plugins/hooks.py
strutex/plugins/plugin_type.py
strutex/plugins/protocol.py
strutex/plugins/registry.py
strutex/plugins/sandbox.py
strutex/postprocessors/__init__.py
strutex/postprocessors/chain.py
strutex/postprocessors/currency.py
strutex/postprocessors/date.py
strutex/postprocessors/number.py
strutex/processor.py
strutex/processors/__init__.py
strutex/processors/active.py
strutex/processors/agentic.py
strutex/processors/base.py
strutex/processors/batch.py
strutex/processors/ensemble.py
strutex/processors/fallback.py
strutex/processors/privacy.py
strutex/processors/rag.py
strutex/processors/router.py
strutex/processors/sequential.py
strutex/processors/simple.py
strutex/processors/verified.py
strutex/prompts/__init__.py
strutex/prompts/builder.py
strutex/providers/__init__.py
strutex/providers/anthropic.py
strutex/providers/base.py
strutex/providers/chain.py
strutex/providers/gemini.py
strutex/providers/groq.py
strutex/providers/hybrid.py
strutex/providers/langdock.py
strutex/providers/ollama.py
strutex/providers/openai.py
strutex/providers/retry.py
strutex/providers/streaming.py
strutex/pydantic_support.py
strutex/rag/__init__.py
strutex-1.3.7.dist-info/METADATA
strutex-1.3.7.dist-info/WHEEL
strutex-1.3.7.dist-info/entry_points.txt
strutex-1.3.7.dist-info/licenses/LICENSE
strutex-1.3.7.dist-info/RECORD
