Metadata-Version: 2.4
Name: strutex
Version: 1.3.7
Summary: Structured AI document processing with robust fallback strategies.
License: GPL-3.0-or-later
License-File: LICENSE
Keywords: pdf,ai,llm,extraction,json
Author: aquiles
Author-email: achillezongo07@gmail.com
Requires-Python: >=3.12,<4.0
Classifier: License :: OSI Approved :: GNU General Public License v3 or later (GPLv3+)
Classifier: Programming Language :: Python :: 3
Classifier: Programming Language :: Python :: 3.12
Classifier: Programming Language :: Python :: 3.13
Classifier: Programming Language :: Python :: 3.14
Provides-Extra: all
Provides-Extra: anthropic
Provides-Extra: cli
Provides-Extra: fallback
Provides-Extra: gliner
Provides-Extra: google
Provides-Extra: groq
Provides-Extra: guardrails
Provides-Extra: haystack
Provides-Extra: langchain
Provides-Extra: llamaindex
Provides-Extra: ocr
Provides-Extra: ollama
Provides-Extra: openai
Provides-Extra: rag
Provides-Extra: server
Requires-Dist: anthropic (>=0.75.0,<0.76.0) ; extra == "anthropic" or extra == "all"
Requires-Dist: click (>=8.1.0,<9.0.0) ; extra == "cli" or extra == "all"
Requires-Dist: fastapi (>=0.128.0,<0.129.0) ; extra == "server" or extra == "all"
Requires-Dist: fastembed (>=0.7.4,<0.8.0) ; extra == "rag" or extra == "all"
Requires-Dist: gliner (>=0.2.0,<0.3.0) ; extra == "gliner" or extra == "all"
Requires-Dist: google-genai (>=1.53.0,<2.0.0) ; extra == "google" or extra == "all"
Requires-Dist: groq (>=1.0.0,<2.0.0) ; extra == "groq" or extra == "all"
Requires-Dist: haystack-ai (>=2.0.0,<3.0.0) ; extra == "haystack" or extra == "all"
Requires-Dist: langchain (>=1.2.1,<2.0.0) ; extra == "rag" or extra == "all"
Requires-Dist: langchain-community (>=0.4.1,<0.5.0) ; extra == "rag" or extra == "all"
Requires-Dist: langchain-core (>=1.2.5,<2.0.0) ; extra == "langchain" or extra == "all"
Requires-Dist: langchain-google-genai (>=4.1.3,<5.0.0) ; extra == "rag" or extra == "all"
Requires-Dist: langchain-openai (>=1.1.6,<2.0.0) ; extra == "rag" or extra == "all"
Requires-Dist: langgraph (>=1.0.5,<2.0.0) ; extra == "rag" or extra == "all"
Requires-Dist: llama-index-core (>=0.14.0,<0.15.0) ; extra == "llamaindex" or extra == "all"
Requires-Dist: numpy (>=2.1.0,<3.0.0) ; extra == "guardrails" or extra == "rag" or extra == "all"
Requires-Dist: ollama (>=0.6.1,<0.7.0) ; extra == "ollama" or extra == "all"
Requires-Dist: openai (>=2.8.1,<3.0.0) ; extra == "openai" or extra == "all"
Requires-Dist: openpyxl (>=3.1.5,<4.0.0)
Requires-Dist: pandas (>=2.3.3,<3.0.0)
Requires-Dist: pdf2image (>=1.17.0,<2.0.0) ; extra == "ocr" or extra == "all"
Requires-Dist: pdfplumber (>=0.11.8,<0.12.0)
Requires-Dist: pluggy (>=1.5.0,<2.0.0)
Requires-Dist: pydantic (>=2.12.5,<3.0.0)
Requires-Dist: pypdf (>=6.4.0,<7.0.0)
Requires-Dist: pytesseract (>=0.3.10,<0.4.0) ; extra == "ocr" or extra == "all"
Requires-Dist: python-dotenv (>=1.2.1,<2.0.0)
Requires-Dist: python-multipart (>=0.0.21,<0.0.22) ; extra == "server" or extra == "all"
Requires-Dist: qdrant-client (>=1.16.2,<2.0.0) ; extra == "rag" or extra == "all"
Requires-Dist: sentence-transformers (>=3.3.0,<4.0.0) ; extra == "guardrails" or extra == "all"
Requires-Dist: unstructured (>=0.11.0,<0.12.0) ; extra == "fallback" or extra == "all"
Requires-Dist: uvicorn (>=0.40.0,<0.41.0) ; extra == "server" or extra == "all"
Project-URL: Homepage, https://github.com/Aquilesorei/strutex
Project-URL: Repository, https://github.com/Aquilesorei/strutex
